{
  "annotations": {
    "list": [
      {
        "builtIn": 1,
        "datasource": {
          "type": "grafana",
          "uid": "-- Grafana --"
        },
        "enable": true,
        "hide": true,
        "iconColor": "rgba(0, 211, 255, 1)",
        "name": "Annotations & Alerts",
        "type": "dashboard"
      }
    ]
  },
  "editable": true,
  "fiscalYearStartMonth": 0,
  "graphTooltip": 0,
  "links": [],
  "liveNow": false,
  "panels": [
    {
      "datasource": {
        "type": "mysql",
        "uid": "fa21b362-00b4-4188-81f1-f491997e9cf6"
      },
      "fieldConfig": {
        "defaults": {
          "color": {
            "mode": "palette-classic"
          },
          "custom": {
            "hideFrom": {
              "legend": false,
              "tooltip": false,
              "viz": false
            }
          },
          "mappings": []
        },
        "overrides": []
      },
      "gridPos": {
        "h": 8,
        "w": 12,
        "x": 0,
        "y": 0
      },
      "id": 2,
      "options": {
        "displayLabels": [
          "value",
          "percent",
          "name"
        ],
        "legend": {
          "calcs": [],
          "displayMode": "hidden",
          "placement": "right",
          "showLegend": false,
          "values": []
        },
        "pieType": "donut",
        "reduceOptions": {
          "calcs": [
            "lastNotNull"
          ],
          "fields": "",
          "values": false
        },
        "tooltip": {
          "mode": "single",
          "sort": "none"
        }
      },
      "targets": [
        {
          "dataset": "indicator",
          "datasource": {
            "type": "mysql",
            "uid": "fa21b362-00b4-4188-81f1-f491997e9cf6"
          },
          "editorMode": "code",
          "format": "table",
          "rawQuery": true,
          "rawSql": "select sum(control) as 설정, sum(blocked) as 차단 from indicator.BlockAccess;",
          "refId": "A",
          "sql": {
            "columns": [
              {
                "parameters": [],
                "type": "function"
              }
            ],
            "groupBy": [
              {
                "property": {
                  "type": "string"
                },
                "type": "groupBy"
              }
            ],
            "limit": 50
          }
        }
      ],
      "title": "해외 접속 차단 설정 또는 해제 계정수(비율)",
      "type": "piechart"
    },
    {
      "datasource": {
        "type": "mysql",
        "uid": "fa21b362-00b4-4188-81f1-f491997e9cf6"
      },
      "fieldConfig": {
        "defaults": {
          "color": {
            "mode": "palette-classic"
          },
          "custom": {
            "axisBorderShow": false,
            "axisCenteredZero": false,
            "axisColorMode": "text",
            "axisLabel": "",
            "axisPlacement": "auto",
            "fillOpacity": 80,
            "gradientMode": "none",
            "hideFrom": {
              "legend": false,
              "tooltip": false,
              "viz": false
            },
            "lineWidth": 1,
            "scaleDistribution": {
              "type": "linear"
            },
            "thresholdsStyle": {
              "mode": "off"
            }
          },
          "mappings": [],
          "thresholds": {
            "mode": "absolute",
            "steps": [
              {
                "color": "green",
                "value": null
              },
              {
                "color": "red",
                "value": 80
              }
            ]
          },
          "unit": "short"
        },
        "overrides": []
      },
      "gridPos": {
        "h": 11,
        "w": 16,
        "x": 0,
        "y": 8
      },
      "id": 1,
      "options": {
        "barRadius": 0,
        "barWidth": 0.97,
        "fullHighlight": false,
        "groupWidth": 0.7,
        "legend": {
          "calcs": [],
          "displayMode": "list",
          "placement": "right",
          "showLegend": true
        },
        "orientation": "auto",
        "showValue": "never",
        "stacking": "none",
        "tooltip": {
          "mode": "single",
          "sort": "none"
        },
        "xTickLabelRotation": 0,
        "xTickLabelSpacing": 0
      },
      "pluginVersion": "10.2.0",
      "targets": [
        {
          "dataset": "indicator",
          "datasource": {
            "type": "mysql",
            "uid": "fa21b362-00b4-4188-81f1-f491997e9cf6"
          },
          "editorMode": "code",
          "format": "table",
          "rawQuery": true,
          "rawSql": "select date, control, blocked from indicator.BlockAccess;",
          "refId": "A",
          "sql": {
            "columns": [
              {
                "parameters": [],
                "type": "function"
              }
            ],
            "groupBy": [
              {
                "property": {
                  "type": "string"
                },
                "type": "groupBy"
              }
            ],
            "limit": 50
          }
        }
      ],
      "title": "해외 접속 차단 설정 또는 해제 계정수",
      "type": "barchart"
    }
  ],
  "refresh": false,
  "schemaVersion": 38,
  "tags": [],
  "templating": {
    "list": []
  },
  "time": {
    "from": "2024-04-30T02:50:40.874Z",
    "to": "2024-04-30T08:50:40.874Z"
  },
  "timepicker": {},
  "timezone": "",
  "title": "sample",
  "uid": "f07c595c-3b84-46a2-874a-77e0a1db8fb3",
  "version": 3,
  "weekStart": ""
}